topsis/__init__.py
topsis/topsis.py
topsis_garima_102303542-0.0.2.dist-info/licenses/LICENSE
topsis_garima_102303542-0.0.2.dist-info/METADATA
topsis_garima_102303542-0.0.2.dist-info/WHEEL
topsis_garima_102303542-0.0.2.dist-info/entry_points.txt
topsis_garima_102303542-0.0.2.dist-info/top_level.txt
topsis_garima_102303542-0.0.2.dist-info/RECORD
