Metadata-Version: 2.4
Name: topsis_garima_102303542
Version: 0.0.2
Summary: TOPSIS implementation in Python (Command Line Tool)
Author: Garima Singla
Author-email: garimasingla732@gmail.com
Requires-Python: >=3.7
License-File: LICENSE
Requires-Dist: numpy
Requires-Dist: pandas
Dynamic: author
Dynamic: author-email
Dynamic: description
Dynamic: description-content-type
Dynamic: license-file
Dynamic: requires-dist
Dynamic: requires-python
Dynamic: summary
